Metadata-Version: 2.1
Name: obscurepy
Version: 0.9.0
Summary: A tool for obscuring, or making python source difficult to read. 
Home-page: https://github.com/drewtchrist/obscurepy
Author: Andrew Christiansen
Author-email: andrewtaylorchristiansen@gmail.com
License: UNKNOWN
Platform: UNKNOWN
Classifier: Programming Language :: Python :: 3
Classifier: License :: OSI Approved :: MIT License
Classifier: Operating System :: OS Independent
Requires-Python: >=3.6
License-File: LICENSE
Requires-Dist: Click
Requires-Dist: astunparse
Requires-Dist: pyyaml
